ehdg_gaze/__init__.py
ehdg_gaze/demo.py
ehdg_gaze/ehdg_gaze.py
ehdg_gaze/gaze_estimator.py
ehdg_gaze/test_main.py
ehdg_gaze/transforms.py
ehdg_gaze/utils.py
ehdg_gaze/__pycache__/__init__.cpython-39.pyc
ehdg_gaze/__pycache__/demo.cpython-39.pyc
ehdg_gaze/__pycache__/gaze_estimator.cpython-39.pyc
ehdg_gaze/__pycache__/test_main.cpython-39.pyc
ehdg_gaze/__pycache__/transforms.cpython-39.pyc
ehdg_gaze/__pycache__/utils.cpython-39.pyc
ehdg_gaze/common/__init__.py
ehdg_gaze/common/camera.py
ehdg_gaze/common/eye.py
ehdg_gaze/common/face.py
ehdg_gaze/common/face_model.py
ehdg_gaze/common/face_model_68.py
ehdg_gaze/common/face_model_mediapipe.py
ehdg_gaze/common/face_parts.py
ehdg_gaze/common/visualizer.py
ehdg_gaze/common/__pycache__/__init__.cpython-39.pyc
ehdg_gaze/common/__pycache__/camera.cpython-39.pyc
ehdg_gaze/common/__pycache__/eye.cpython-39.pyc
ehdg_gaze/common/__pycache__/face.cpython-39.pyc
ehdg_gaze/common/__pycache__/face_model.cpython-39.pyc
ehdg_gaze/common/__pycache__/face_model_68.cpython-39.pyc
ehdg_gaze/common/__pycache__/face_model_mediapipe.cpython-39.pyc
ehdg_gaze/common/__pycache__/face_parts.cpython-39.pyc
ehdg_gaze/common/__pycache__/visualizer.cpython-39.pyc
ehdg_gaze/data/calib/sample_params.yaml
ehdg_gaze/data/configs/eth-xgaze.yaml
ehdg_gaze/data/configs/mpiifacegaze.yaml
ehdg_gaze/data/configs/mpiigaze.yaml
ehdg_gaze/data/normalized_camera_params/eth-xgaze.yaml
ehdg_gaze/data/normalized_camera_params/mpiifacegaze.yaml
ehdg_gaze/data/normalized_camera_params/mpiigaze.yaml
ehdg_gaze/head_pose_estimation/__init__.py
ehdg_gaze/head_pose_estimation/face_landmark_estimator.py
ehdg_gaze/head_pose_estimation/head_pose_normalizer.py
ehdg_gaze/head_pose_estimation/__pycache__/__init__.cpython-39.pyc
ehdg_gaze/head_pose_estimation/__pycache__/face_landmark_estimator.cpython-39.pyc
ehdg_gaze/head_pose_estimation/__pycache__/head_pose_normalizer.cpython-39.pyc
ehdg_gaze/models/__init__.py
ehdg_gaze/models/eth-xgaze_resnet18.pth
ehdg_gaze-1.1.2.dist-info/licenses/LICENSE
ehdg_gaze-1.1.2.dist-info/METADATA
ehdg_gaze-1.1.2.dist-info/WHEEL
ehdg_gaze-1.1.2.dist-info/entry_points.txt
ehdg_gaze-1.1.2.dist-info/top_level.txt
ehdg_gaze-1.1.2.dist-info/RECORD
